setup.py
digServiceExtractor/__init__.py
digServiceExtractor/names.py
digServiceExtractor/names_helper.py
digServiceExtractor.egg-info/PKG-INFO
digServiceExtractor.egg-info/SOURCES.txt
digServiceExtractor.egg-info/dependency_links.txt
digServiceExtractor.egg-info/requires.txt
digServiceExtractor.egg-info/top_level.txt
test/__init__.py
test/test_service_extractor.py