Metadata-Version: 1.1
Name: digServiceExtractor
Version: 0.3.0
Summary: digServiceExtractor
Home-page: https://github.com/usc-isi-i2/dig-service-extractor
Author: Lingzhe Teng
Author-email: zwein27@gmail.com
License: UNKNOWN
Download-URL: https://github.com/usc-isi-i2/dig-service-extractor
Keywords: service,extractor
Platform: UNKNOWN
